setup.py
wasif/Binomialdistribution.py
wasif/Gaussiandistribution.py
wasif/Generaldistribution.py
wasif/__init__.py
wasif.egg-info/PKG-INFO
wasif.egg-info/SOURCES.txt
wasif.egg-info/dependency_links.txt
wasif.egg-info/not-zip-safe
wasif.egg-info/top_level.txt