Metadata-Version: 1.0
Name: wasif
Version: 0.1
Summary: Gaussian distributions
Home-page: UNKNOWN
Author: Wasif Ibrahim
Author-email: wasif.ibrahim29@gmail.com
License: UNKNOWN
Platform: UNKNOWN
